MANIFEST.in
README.md
requirements.txt
setup.py
epsolar_tracer/Coil.py
epsolar_tracer/Register.py
epsolar_tracer/Value.py
epsolar_tracer/__init__.py
epsolar_tracer/client.py
epsolar_tracer/registers.py
epsolar_tracer/units.py
epsolar_tracer.egg-info/PKG-INFO
epsolar_tracer.egg-info/SOURCES.txt
epsolar_tracer.egg-info/dependency_links.txt
epsolar_tracer.egg-info/requires.txt
epsolar_tracer.egg-info/top_level.txt
epsolar_tracer/enums/CoilTypeEnum.py
epsolar_tracer/enums/RegisterTypeEnum.py
epsolar_tracer/enums/__init__.py
test/__init__.py
test/testdata.py
tests/__init__.py