Metadata-Version: 1.1
Name: epsolar-tracer
Version: 0.0.8
Summary: Tools for EPsolar Tracer A and BN solar charge controller
Home-page: https://github.com/Salamek/epsolar-tracer
Author: Adam Schubert
Author-email: adam.schubert@sg1-game.net
License: Apache License 2.0
Platform: UNKNOWN
Classifier: Development Status :: 4 - Beta
Classifier: Intended Audience :: Developers
Classifier: Programming Language :: Python
Classifier: Programming Language :: Python :: 3
Classifier: Programming Language :: Python :: 3.3
Classifier: Programming Language :: Python :: 3.4
Classifier: Programming Language :: Python :: 3.5
Classifier: Programming Language :: Python :: 3.6
Classifier: Programming Language :: Python :: Implementation :: CPython
Classifier: Programming Language :: Python :: Implementation :: PyPy
Classifier: Operating System :: OS Independent
